CHANGES.rst
CONTRIBUTORS.rst
MANIFEST.in
README.rst
setup.cfg
setup.py
docs/LICENSE.GPL
docs/LICENSE.txt
src/collective/__init__.py
src/collective.aviary.egg-info/PKG-INFO
src/collective.aviary.egg-info/SOURCES.txt
src/collective.aviary.egg-info/dependency_links.txt
src/collective.aviary.egg-info/entry_points.txt
src/collective.aviary.egg-info/namespace_packages.txt
src/collective.aviary.egg-info/not-zip-safe
src/collective.aviary.egg-info/requires.txt
src/collective.aviary.egg-info/top_level.txt
src/collective/aviary/__init__.py
src/collective/aviary/config.py
src/collective/aviary/configure.zcml
src/collective/aviary/controlpanel.py
src/collective/aviary/interfaces.py
src/collective/aviary/profiles.zcml
src/collective/aviary/testing.py
src/collective/aviary/vocabularies.py
src/collective/aviary/Extensions/Install.py
src/collective/aviary/Extensions/__init__.py
src/collective/aviary/browser/__init__.py
src/collective/aviary/browser/configure.zcml
src/collective/aviary/browser/view.py
src/collective/aviary/browser/templates/aviary_transform.pt
src/collective/aviary/locales/collective.aviary.pot
src/collective/aviary/locales/manual.pot
src/collective/aviary/locales/plone.pot
src/collective/aviary/locales/es/LC_MESSAGES/collective.aviary.mo
src/collective/aviary/locales/es/LC_MESSAGES/collective.aviary.po
src/collective/aviary/locales/es/LC_MESSAGES/plone.mo
src/collective/aviary/locales/es/LC_MESSAGES/plone.po
src/collective/aviary/locales/pt_BR/LC_MESSAGES/collective.aviary.mo
src/collective/aviary/locales/pt_BR/LC_MESSAGES/collective.aviary.po
src/collective/aviary/locales/pt_BR/LC_MESSAGES/plone.mo
src/collective/aviary/locales/pt_BR/LC_MESSAGES/plone.po
src/collective/aviary/profiles/default/browserlayer.xml
src/collective/aviary/profiles/default/controlpanel.xml
src/collective/aviary/profiles/default/metadata.xml
src/collective/aviary/profiles/default/registry.xml
src/collective/aviary/profiles/uninstall/registry.xml
src/collective/aviary/static/aviary.png
src/collective/aviary/static/aviary_icon.png
src/collective/aviary/tests/__init__.py
src/collective/aviary/tests/test_controlpanel.py
src/collective/aviary/tests/test_robot.py
src/collective/aviary/tests/test_setup.py
src/collective/aviary/tests/test_transform_view.robot
src/collective/aviary/tests/test_vocabularies.py